<?xml version="1.0" encoding="UTF-8"?><vehicle data_version="2" is_advanced="false" is_static="false" bodies_id="159"><editor_placement_offset x="0" y="0" z="0"/><authors/><bodies><body unique_id="159"><initial_local_transform 00="1" 01="0" 02="0" 03="0" 10="0" 11="1" 12="0" 13="0" 20="0" 21="0" 22="1" 23="0" 30="0" 31="0" 32="0" 33="1"/><local_transform 00="1" 01="0" 02="0" 03="0" 10="0" 11="1" 12="0" 13="0" 20="0" 21="0" 22="1" 23="0" 30="0" 31="0" 32="0" 33="1"/><components><c d="ladder_small" t="0"><o r="1,0,0,0,0,1,0,-1,0" bc="141414FF" ac="141414FF" sc="11" custom_name=""><vp x="0" y="1" z="0"/></o></c><c d="ladder_small" t="0"><o r="1,0,0,0,0,1,0,-1,0" bc="141414FF" ac="141414FF" sc="11" custom_name=""><vp x="0" y="2" z="0"/></o></c><c d="ladder_small" t="0"><o r="1,0,0,0,0,1,0,-1,0" bc="141414FF" ac="141414FF" sc="11" custom_name=""><vp x="0" y="3" z="0"/></o></c><c d="ladder_small" t="0"><o r="1,0,0,0,0,1,0,-1,0" bc="141414FF" ac="141414FF" sc="11" custom_name=""><vp x="0" y="4" z="0"/></o></c><c d="ladder_small" t="0"><o r="1,0,0,0,0,1,0,-1,0" bc="141414FF" ac="141414FF" sc="11" custom_name=""><vp x="0" y="5" z="0"/></o></c><c d="ladder_small" t="0"><o r="1,0,0,0,0,1,0,-1,0" bc="141414FF" ac="141414FF" sc="11" custom_name=""><vp x="0" y="6" z="0"/></o></c><c d="ladder_small" t="0"><o r="1,0,0,0,0,1,0,-1,0" bc="141414FF" ac="141414FF" sc="11" custom_name=""><vp x="0" y="7" z="0"/></o></c><c d="ladder_small" t="0"><o r="1,0,0,0,0,1,0,-1,0" bc="141414FF" ac="141414FF" sc="11" custom_name=""><vp x="0" y="8" z="0"/></o></c><c d="ladder_small" t="0"><o r="1,0,0,0,0,1,0,-1,0" bc="141414FF" ac="141414FF" sc="11" custom_name=""><vp x="0" y="9" z="0"/></o></c><c d="ladder_small" t="0"><o r="1,0,0,0,0,1,0,-1,0" bc="141414FF" ac="141414FF" sc="11" custom_name=""><vp x="0" y="10" z="0"/></o></c><c d="ladder_small" t="0"><o r="1,0,0,0,0,1,0,-1,0" bc="141414FF" ac="141414FF" sc="11" custom_name=""><vp x="0" y="11" z="0"/></o></c><c d="ladder_small" t="0"><o r="1,0,0,0,0,1,0,-1,0" bc="141414FF" ac="141414FF" sc="11" custom_name=""><vp x="0" y="12" z="0"/></o></c><c d="ladder_small" t="0"><o r="1,0,0,0,0,1,0,-1,0" bc="141414FF" ac="141414FF" sc="11" custom_name=""><vp x="0" y="13" z="0"/></o></c><c d="ladder_small" t="0"><o r="1,0,0,0,0,1,0,-1,0" bc="141414FF" ac="141414FF" sc="11" custom_name=""><vp x="0" y="14" z="0"/></o></c><c d="ladder_small" t="0"><o r="1,0,0,0,0,1,0,-1,0" bc="141414FF" ac="141414FF" sc="11" custom_name=""><vp x="0" y="15" z="0"/></o></c><c d="ladder_small" t="0"><o r="1,0,0,0,0,1,0,-1,0" bc="141414FF" ac="141414FF" sc="11" custom_name=""><vp x="0" y="16" z="0"/></o></c><c d="ladder_small" t="0"><o r="1,0,0,0,0,1,0,-1,0" bc="141414FF" ac="141414FF" sc="11" custom_name=""><vp x="0" y="17" z="0"/></o></c><c d="ladder_small" t="0"><o r="1,0,0,0,0,1,0,-1,0" bc="141414FF" ac="141414FF" sc="11" custom_name=""><vp x="0" y="18" z="0"/></o></c><c d="ladder_small" t="0"><o r="1,0,0,0,0,1,0,-1,0" bc="141414FF" ac="141414FF" sc="11" custom_name=""><vp x="0" y="19" z="0"/></o></c><c d="ladder_small" t="0"><o r="1,0,0,0,0,1,0,-1,0" bc="141414FF" ac="141414FF" sc="11" custom_name=""><vp x="0" y="20" z="0"/></o></c><c d="ladder_small" t="0"><o r="1,0,0,0,0,1,0,-1,0" bc="141414FF" ac="141414FF" sc="11" custom_name=""><vp x="0" y="21" z="0"/></o></c><c d="ladder_small" t="0"><o r="1,0,0,0,0,1,0,-1,0" bc="141414FF" ac="141414FF" sc="11" custom_name=""><vp x="0" y="22" z="0"/></o></c><c d="ladder_small" t="0"><o r="1,0,0,0,0,1,0,-1,0" bc="141414FF" ac="141414FF" sc="11" custom_name=""><vp x="0" y="23" z="0"/></o></c><c d="ladder_small" t="0"><o r="1,0,0,0,0,1,0,-1,0" bc="141414FF" ac="141414FF" sc="11" custom_name=""><vp x="0" y="24" z="0"/></o></c><c d="ladder_small" t="0"><o r="1,0,0,0,0,1,0,-1,0" bc="141414FF" ac="141414FF" sc="11" custom_name=""><vp x="0" y="25" z="0"/></o></c><c d="ladder_small" t="0"><o r="1,0,0,0,0,1,0,-1,0" bc="141414FF" ac="141414FF" sc="11" custom_name=""><vp x="0" y="26" z="0"/></o></c><c d="ladder_small" t="0"><o r="1,0,0,0,0,1,0,-1,0" bc="141414FF" ac="141414FF" sc="11" custom_name=""><vp x="0" y="27" z="0"/></o></c><c d="ladder_small" t="0"><o r="1,0,0,0,0,1,0,-1,0" bc="141414FF" ac="141414FF" sc="11" custom_name=""><vp x="0" y="28" z="0"/></o></c><c d="ladder_small" t="0"><o r="1,0,0,0,0,1,0,-1,0" bc="141414FF" ac="141414FF" sc="11" custom_name=""><vp x="0" y="29" z="0"/></o></c><c d="ladder_small" t="0"><o r="1,0,0,0,0,1,0,-1,0" bc="141414FF" ac="141414FF" sc="11" custom_name=""><vp x="0" y="30" z="0"/></o></c><c d="ladder_small" t="0"><o r="1,0,0,0,0,1,0,-1,0" bc="141414FF" ac="141414FF" sc="11" custom_name=""><vp x="0" y="31" z="0"/></o></c><c d="ladder_small" t="0"><o r="1,0,0,0,0,1,0,-1,0" bc="141414FF" ac="141414FF" sc="11" custom_name=""><vp x="0" y="32" z="0"/></o></c><c d="ladder_small" t="0"><o r="1,0,0,0,0,1,0,-1,0" bc="141414FF" ac="141414FF" sc="11" custom_name=""><vp x="0" y="33" z="0"/></o></c><c d="ladder_small" t="0"><o r="1,0,0,0,0,1,0,-1,0" bc="141414FF" ac="141414FF" sc="11" custom_name=""><vp x="0" y="34" z="0"/></o></c><c d="ladder_small" t="0"><o r="1,0,0,0,0,1,0,-1,0" bc="141414FF" ac="141414FF" sc="11" custom_name=""><vp x="0" y="35" z="0"/></o></c><c d="ladder_small" t="0"><o r="1,0,0,0,0,1,0,-1,0" bc="141414FF" ac="141414FF" sc="11" custom_name=""><vp x="0" y="36" z="0"/></o></c></components></body></bodies><logic_node_links/></vehicle>