<?xml version="1.0" encoding="UTF-8"?><vehicle data_version="2" is_advanced="true" is_static="true" bodies_id="45"><editor_placement_offset x="0" y="0" z="0"/><authors/><bodies><body unique_id="45"><initial_local_transform 00="1" 01="0" 02="0" 03="0" 10="0" 11="1" 12="0" 13="0" 20="0" 21="0" 22="1" 23="0" 30="0" 31="0" 32="0" 33="1"/><local_transform 00="1" 01="0" 02="0" 03="0" 10="0" 11="1" 12="0" 13="0" 20="0" 21="0" 22="1" 23="0" 30="0" 31="0" 32="0" 33="1"/><components><c d="01_block" t="0"><o r="1,0,0,0,1,0,0,0,1" bc="FFFFFFFF" ac="FFFFFFFF" sc="6"><vp x="0" y="0" z="0"/></o></c><c d="01_block" t="0"><o r="1,0,0,0,0,1,0,-1,0" bc="FFFFFFFF" ac="FFFFFFFF" sc="6"><vp x="0" y="0" z="1"/></o></c><c d="01_block" t="0"><o r="1,0,0,0,0,1,0,-1,0" bc="FFFFFFFF" ac="FFFFFFFF" sc="6"><vp x="0" y="0" z="2"/></o></c><c d="01_block" t="0"><o r="1,0,0,0,1,0,0,0,1" bc="FFFFFFFF" ac="FFFFFFFF" sc="6"><vp x="0" y="1" z="0"/></o></c><c d="01_block" t="0"><o r="1,0,0,0,1,0,0,0,1" bc="FFFFFFFF" ac="FFFFFFFF" sc="6"><vp x="0" y="1" z="1"/></o></c><c d="01_block" t="0"><o r="1,0,0,0,1,0,0,0,1" bc="FFFFFFFF" ac="FFFFFFFF" sc="6"><vp x="0" y="1" z="2"/></o></c><c d="01_block" t="0"><o r="1,0,0,0,1,0,0,0,1" bc="FFFFFFFF" ac="FFFFFFFF" sc="6"><vp x="0" y="2" z="0"/></o></c><c d="01_block" t="0"><o r="1,0,0,0,1,0,0,0,1" bc="FFFFFFFF" ac="FFFFFFFF" sc="6"><vp x="0" y="2" z="1"/></o></c><c d="01_block" t="0"><o r="1,0,0,0,1,0,0,0,1" bc="FFFFFFFF" ac="FFFFFFFF" sc="6"><vp x="0" y="2" z="2"/></o></c><c d="01_block" t="0"><o r="1,0,0,0,1,0,0,0,1" bc="FFFFFFFF" ac="FFFFFFFF" sc="6"><vp x="0" y="3" z="0"/></o></c><c d="01_block" t="0"><o r="1,0,0,0,1,0,0,0,1" bc="FFFFFFFF" ac="FFFFFFFF" sc="6"><vp x="0" y="3" z="1"/></o></c><c d="01_block" t="0"><o r="1,0,0,0,1,0,0,0,1" bc="FFFFFFFF" ac="FFFFFFFF" sc="6"><vp x="0" y="3" z="2"/></o></c><c d="01_block" t="0"><o r="1,0,0,0,1,0,0,0,1" bc="FFFFFFFF" ac="FFFFFFFF" sc="6"><vp x="0" y="4" z="0"/></o></c><c d="01_block" t="0"><o r="1,0,0,0,1,0,0,0,1" bc="FFFFFFFF" ac="FFFFFFFF" sc="6"><vp x="0" y="4" z="1"/></o></c><c d="01_block" t="0"><o r="1,0,0,0,1,0,0,0,1" bc="FFFFFFFF" ac="FFFFFFFF" sc="6"><vp x="0" y="4" z="2"/></o></c><c d="01_block" t="0"><o r="1,0,0,0,0,1,0,-1,0" bc="FFFFFFFF" ac="FFFFFFFF" sc="6"><vp x="0" y="1" z="3"/></o></c><c d="01_block" t="0"><o r="1,0,0,0,0,1,0,-1,0" bc="FFFFFFFF" ac="FFFFFFFF" sc="6"><vp x="0" y="2" z="3"/></o></c><c d="01_block" t="0"><o r="1,0,0,0,0,1,0,-1,0" bc="FFFFFFFF" ac="FFFFFFFF" sc="6"><vp x="0" y="3" z="3"/></o></c><c d="01_block" t="0"><o r="1,0,0,0,0,-1,0,1,0" bc="FFFFFFFF" ac="FFFFFFFF" sc="6"><vp x="0" y="1" z="-1"/></o></c><c d="01_block" t="0"><o r="1,0,0,0,0,-1,0,1,0" bc="FFFFFFFF" ac="FFFFFFFF" sc="6"><vp x="0" y="2" z="-1"/></o></c><c d="01_block" t="0"><o r="1,0,0,0,0,-1,0,1,0" bc="FFFFFFFF" ac="FFFFFFFF" sc="6"><vp x="0" y="3" z="-1"/></o></c><c d="01_block" t="0"><o r="1,0,0,0,0,-1,0,1,0" bc="FFFFFFFF" ac="FFFFFFFF" sc="6"><vp x="0" y="1" z="-2"/></o></c><c d="01_block" t="0"><o r="1,0,0,0,0,-1,0,1,0" bc="FFFFFFFF" ac="FFFFFFFF" sc="6"><vp x="0" y="2" z="-2"/></o></c><c d="01_block" t="0"><o r="1,0,0,0,0,-1,0,1,0" bc="FFFFFFFF" ac="FFFFFFFF" sc="6"><vp x="0" y="3" z="-2"/></o></c><c d="01_block" t="0"><o r="1,0,0,0,0,-1,0,1,0" bc="FFFFFFFF" ac="FFFFFFFF" sc="6"><vp x="0" y="4" z="-2"/></o></c><c d="01_block" t="0"><o r="1,0,0,0,0,-1,0,1,0" bc="FFFFFFFF" ac="FFFFFFFF" sc="6"><vp x="0" y="5" z="-2"/></o></c><c d="01_block" t="0"><o r="1,0,0,0,0,-1,0,1,0" bc="FFFFFFFF" ac="FFFFFFFF" sc="6"><vp x="0" y="6" z="-2"/></o></c><c d="01_block" t="0"><o r="1,0,0,0,0,-1,0,1,0" bc="FFFFFFFF" ac="FFFFFFFF" sc="6"><vp x="0" y="7" z="-2"/></o></c><c d="01_block" t="0"><o r="1,0,0,0,0,-1,0,1,0" bc="FFFFFFFF" ac="FFFFFFFF" sc="6"><vp x="0" y="8" z="-2"/></o></c><c d="01_block" t="0"><o r="1,0,0,0,0,-1,0,1,0" bc="FFFFFFFF" ac="FFFFFFFF" sc="6"><vp x="0" y="9" z="-2"/></o></c><c d="01_block" t="0"><o r="1,0,0,0,0,-1,0,1,0" bc="FFFFFFFF" ac="FFFFFFFF" sc="6"><vp x="0" y="10" z="-2"/></o></c><c d="01_block" t="0"><o r="1,0,0,0,0,-1,0,1,0" bc="FFFFFFFF" ac="FFFFFFFF" sc="6"><vp x="0" y="11" z="-2"/></o></c><c d="01_block" t="0"><o r="1,0,0,0,0,-1,0,1,0" bc="FFFFFFFF" ac="FFFFFFFF" sc="6"><vp x="0" y="12" z="-2"/></o></c><c d="01_block" t="0"><o r="1,0,0,0,0,-1,0,1,0" bc="FFFFFFFF" ac="FFFFFFFF" sc="6"><vp x="0" y="13" z="-2"/></o></c><c d="01_block" t="0"><o r="1,0,0,0,0,-1,0,1,0" bc="FFFFFFFF" ac="FFFFFFFF" sc="6"><vp x="0" y="14" z="-2"/></o></c><c d="01_block" t="0"><o r="1,0,0,0,0,-1,0,1,0" bc="FFFFFFFF" ac="FFFFFFFF" sc="6"><vp x="0" y="15" z="-2"/></o></c><c d="01_block" t="0"><o r="1,0,0,0,0,-1,0,1,0" bc="FFFFFFFF" ac="FFFFFFFF" sc="6"><vp x="0" y="16" z="-2"/></o></c><c d="01_block" t="0"><o r="1,0,0,0,0,-1,0,1,0" bc="FFFFFFFF" ac="FFFFFFFF" sc="6"><vp x="0" y="17" z="-2"/></o></c><c d="01_block" t="0"><o r="1,0,0,0,0,-1,0,1,0" bc="FFFFFFFF" ac="FFFFFFFF" sc="6"><vp x="0" y="18" z="-2"/></o></c><c d="01_block" t="0"><o r="1,0,0,0,0,-1,0,1,0" bc="FFFFFFFF" ac="FFFFFFFF" sc="6"><vp x="0" y="19" z="-2"/></o></c><c d="01_block" t="0"><o r="1,0,0,0,0,-1,0,1,0" bc="FFFFFFFF" ac="FFFFFFFF" sc="6"><vp x="0" y="1" z="-3"/></o></c><c d="01_block" t="0"><o r="1,0,0,0,0,-1,0,1,0" bc="FFFFFFFF" ac="FFFFFFFF" sc="6"><vp x="0" y="2" z="-3"/></o></c><c d="01_block" t="0"><o r="1,0,0,0,0,-1,0,1,0" bc="FFFFFFFF" ac="FFFFFFFF" sc="6"><vp x="0" y="3" z="-3"/></o></c><c d="01_block" t="0"><o r="1,0,0,0,0,-1,0,1,0" bc="FFFFFFFF" ac="FFFFFFFF" sc="6"><vp x="0" y="4" z="-3"/></o></c><c d="01_block" t="0"><o r="1,0,0,0,0,-1,0,1,0" bc="FFFFFFFF" ac="FFFFFFFF" sc="6"><vp x="0" y="5" z="-3"/></o></c><c d="01_block" t="0"><o r="1,0,0,0,0,-1,0,1,0" bc="FFFFFFFF" ac="FFFFFFFF" sc="6"><vp x="0" y="6" z="-3"/></o></c><c d="01_block" t="0"><o r="1,0,0,0,0,-1,0,1,0" bc="FFFFFFFF" ac="FFFFFFFF" sc="6"><vp x="0" y="7" z="-3"/></o></c><c d="01_block" t="0"><o r="1,0,0,0,0,-1,0,1,0" bc="FFFFFFFF" ac="FFFFFFFF" sc="6"><vp x="0" y="8" z="-3"/></o></c><c d="01_block" t="0"><o r="1,0,0,0,0,-1,0,1,0" bc="FFFFFFFF" ac="FFFFFFFF" sc="6"><vp x="0" y="9" z="-3"/></o></c><c d="01_block" t="0"><o r="1,0,0,0,0,-1,0,1,0" bc="FFFFFFFF" ac="FFFFFFFF" sc="6"><vp x="0" y="10" z="-3"/></o></c><c d="01_block" t="0"><o r="1,0,0,0,0,-1,0,1,0" bc="FFFFFFFF" ac="FFFFFFFF" sc="6"><vp x="0" y="11" z="-3"/></o></c><c d="01_block" t="0"><o r="1,0,0,0,0,-1,0,1,0" bc="FFFFFFFF" ac="FFFFFFFF" sc="6"><vp x="0" y="12" z="-3"/></o></c><c d="01_block" t="0"><o r="1,0,0,0,0,-1,0,1,0" bc="FFFFFFFF" ac="FFFFFFFF" sc="6"><vp x="0" y="13" z="-3"/></o></c><c d="01_block" t="0"><o r="1,0,0,0,0,-1,0,1,0" bc="FFFFFFFF" ac="FFFFFFFF" sc="6"><vp x="0" y="14" z="-3"/></o></c><c d="01_block" t="0"><o r="1,0,0,0,0,-1,0,1,0" bc="FFFFFFFF" ac="FFFFFFFF" sc="6"><vp x="0" y="15" z="-3"/></o></c><c d="01_block" t="0"><o r="1,0,0,0,0,-1,0,1,0" bc="FFFFFFFF" ac="FFFFFFFF" sc="6"><vp x="0" y="16" z="-3"/></o></c><c d="01_block" t="0"><o r="1,0,0,0,0,-1,0,1,0" bc="FFFFFFFF" ac="FFFFFFFF" sc="6"><vp x="0" y="17" z="-3"/></o></c><c d="01_block" t="0"><o r="1,0,0,0,0,-1,0,1,0" bc="FFFFFFFF" ac="FFFFFFFF" sc="6"><vp x="0" y="18" z="-3"/></o></c><c d="01_block" t="0"><o r="1,0,0,0,0,-1,0,1,0" bc="FFFFFFFF" ac="FFFFFFFF" sc="6"><vp x="0" y="19" z="-3"/></o></c><c d="01_block" t="0"><o r="1,0,0,0,0,-1,0,1,0" bc="FFFFFFFF" ac="FFFFFFFF" sc="6"><vp x="0" y="1" z="-4"/></o></c><c d="01_block" t="0"><o r="1,0,0,0,0,-1,0,1,0" bc="FFFFFFFF" ac="FFFFFFFF" sc="6"><vp x="0" y="2" z="-4"/></o></c><c d="01_block" t="0"><o r="1,0,0,0,0,-1,0,1,0" bc="FFFFFFFF" ac="FFFFFFFF" sc="6"><vp x="0" y="3" z="-4"/></o></c><c d="01_block" t="0"><o r="1,0,0,0,0,-1,0,1,0" bc="FFFFFFFF" ac="FFFFFFFF" sc="6"><vp x="0" y="4" z="-4"/></o></c><c d="01_block" t="0"><o r="1,0,0,0,0,-1,0,1,0" bc="FFFFFFFF" ac="FFFFFFFF" sc="6"><vp x="0" y="5" z="-4"/></o></c><c d="01_block" t="0"><o r="1,0,0,0,0,-1,0,1,0" bc="FFFFFFFF" ac="FFFFFFFF" sc="6"><vp x="0" y="6" z="-4"/></o></c><c d="01_block" t="0"><o r="1,0,0,0,0,-1,0,1,0" bc="FFFFFFFF" ac="FFFFFFFF" sc="6"><vp x="0" y="7" z="-4"/></o></c><c d="01_block" t="0"><o r="1,0,0,0,0,-1,0,1,0" bc="FFFFFFFF" ac="FFFFFFFF" sc="6"><vp x="0" y="8" z="-4"/></o></c><c d="01_block" t="0"><o r="1,0,0,0,0,-1,0,1,0" bc="FFFFFFFF" ac="FFFFFFFF" sc="6"><vp x="0" y="9" z="-4"/></o></c><c d="01_block" t="0"><o r="1,0,0,0,0,-1,0,1,0" bc="FFFFFFFF" ac="FFFFFFFF" sc="6"><vp x="0" y="10" z="-4"/></o></c><c d="01_block" t="0"><o r="1,0,0,0,0,-1,0,1,0" bc="FFFFFFFF" ac="FFFFFFFF" sc="6"><vp x="0" y="11" z="-4"/></o></c><c d="01_block" t="0"><o r="1,0,0,0,0,-1,0,1,0" bc="FFFFFFFF" ac="FFFFFFFF" sc="6"><vp x="0" y="12" z="-4"/></o></c><c d="01_block" t="0"><o r="1,0,0,0,0,-1,0,1,0" bc="FFFFFFFF" ac="FFFFFFFF" sc="6"><vp x="0" y="13" z="-4"/></o></c><c d="01_block" t="0"><o r="1,0,0,0,0,-1,0,1,0" bc="FFFFFFFF" ac="FFFFFFFF" sc="6"><vp x="0" y="14" z="-4"/></o></c><c d="01_block" t="0"><o r="1,0,0,0,0,-1,0,1,0" bc="FFFFFFFF" ac="FFFFFFFF" sc="6"><vp x="0" y="15" z="-4"/></o></c><c d="01_block" t="0"><o r="1,0,0,0,0,-1,0,1,0" bc="FFFFFFFF" ac="FFFFFFFF" sc="6"><vp x="0" y="16" z="-4"/></o></c><c d="01_block" t="0"><o r="1,0,0,0,0,-1,0,1,0" bc="FFFFFFFF" ac="FFFFFFFF" sc="6"><vp x="0" y="17" z="-4"/></o></c><c d="01_block" t="0"><o r="1,0,0,0,0,-1,0,1,0" bc="FFFFFFFF" ac="FFFFFFFF" sc="6"><vp x="0" y="18" z="-4"/></o></c><c d="01_block" t="0"><o r="1,0,0,0,0,-1,0,1,0" bc="FFFFFFFF" ac="FFFFFFFF" sc="6"><vp x="0" y="19" z="-4"/></o></c><c d="01_block" t="0"><o r="1,0,0,0,0,-1,0,1,0" bc="FFFFFFFF" ac="FFFFFFFF" sc="6"><vp x="0" y="1" z="-5"/></o></c><c d="01_block" t="0"><o r="1,0,0,0,0,-1,0,1,0" bc="FFFFFFFF" ac="FFFFFFFF" sc="6"><vp x="0" y="2" z="-5"/></o></c><c d="01_block" t="0"><o r="1,0,0,0,0,-1,0,1,0" bc="FFFFFFFF" ac="FFFFFFFF" sc="6"><vp x="0" y="3" z="-5"/></o></c><c d="01_block" t="0"><o r="1,0,0,0,0,-1,0,1,0" bc="FFFFFFFF" ac="FFFFFFFF" sc="6"><vp x="0" y="4" z="-5"/></o></c><c d="01_block" t="0"><o r="1,0,0,0,0,-1,0,1,0" bc="FFFFFFFF" ac="FFFFFFFF" sc="6"><vp x="0" y="5" z="-5"/></o></c><c d="01_block" t="0"><o r="1,0,0,0,0,-1,0,1,0" bc="FFFFFFFF" ac="FFFFFFFF" sc="6"><vp x="0" y="6" z="-5"/></o></c><c d="01_block" t="0"><o r="1,0,0,0,0,-1,0,1,0" bc="FFFFFFFF" ac="FFFFFFFF" sc="6"><vp x="0" y="7" z="-5"/></o></c><c d="01_block" t="0"><o r="1,0,0,0,0,-1,0,1,0" bc="FFFFFFFF" ac="FFFFFFFF" sc="6"><vp x="0" y="8" z="-5"/></o></c><c d="01_block" t="0"><o r="1,0,0,0,0,-1,0,1,0" bc="FFFFFFFF" ac="FFFFFFFF" sc="6"><vp x="0" y="9" z="-5"/></o></c><c d="01_block" t="0"><o r="1,0,0,0,0,-1,0,1,0" bc="FFFFFFFF" ac="FFFFFFFF" sc="6"><vp x="0" y="10" z="-5"/></o></c><c d="01_block" t="0"><o r="1,0,0,0,0,-1,0,1,0" bc="FFFFFFFF" ac="FFFFFFFF" sc="6"><vp x="0" y="11" z="-5"/></o></c><c d="01_block" t="0"><o r="1,0,0,0,0,-1,0,1,0" bc="FFFFFFFF" ac="FFFFFFFF" sc="6"><vp x="0" y="12" z="-5"/></o></c><c d="01_block" t="0"><o r="1,0,0,0,0,-1,0,1,0" bc="FFFFFFFF" ac="FFFFFFFF" sc="6"><vp x="0" y="13" z="-5"/></o></c><c d="01_block" t="0"><o r="1,0,0,0,0,-1,0,1,0" bc="FFFFFFFF" ac="FFFFFFFF" sc="6"><vp x="0" y="14" z="-5"/></o></c><c d="01_block" t="0"><o r="1,0,0,0,0,-1,0,1,0" bc="FFFFFFFF" ac="FFFFFFFF" sc="6"><vp x="0" y="15" z="-5"/></o></c><c d="01_block" t="0"><o r="1,0,0,0,0,-1,0,1,0" bc="FFFFFFFF" ac="FFFFFFFF" sc="6"><vp x="0" y="16" z="-5"/></o></c><c d="01_block" t="0"><o r="1,0,0,0,0,-1,0,1,0" bc="FFFFFFFF" ac="FFFFFFFF" sc="6"><vp x="0" y="17" z="-5"/></o></c><c d="01_block" t="0"><o r="1,0,0,0,0,-1,0,1,0" bc="FFFFFFFF" ac="FFFFFFFF" sc="6"><vp x="0" y="18" z="-5"/></o></c><c d="01_block" t="0"><o r="1,0,0,0,0,-1,0,1,0" bc="FFFFFFFF" ac="FFFFFFFF" sc="6"><vp x="0" y="19" z="-5"/></o></c><c d="01_block" t="0"><o r="1,0,0,0,0,-1,0,1,0" bc="FFFFFFFF" ac="FFFFFFFF" sc="6"><vp x="0" y="1" z="-6"/></o></c><c d="01_block" t="0"><o r="1,0,0,0,0,-1,0,1,0" bc="FFFFFFFF" ac="FFFFFFFF" sc="6"><vp x="0" y="2" z="-6"/></o></c><c d="01_block" t="0"><o r="1,0,0,0,0,-1,0,1,0" bc="FFFFFFFF" ac="FFFFFFFF" sc="6"><vp x="0" y="3" z="-6"/></o></c><c d="01_block" t="0"><o r="1,0,0,0,0,-1,0,1,0" bc="FFFFFFFF" ac="FFFFFFFF" sc="6"><vp x="0" y="4" z="-6"/></o></c><c d="01_block" t="0"><o r="1,0,0,0,0,-1,0,1,0" bc="FFFFFFFF" ac="FFFFFFFF" sc="6"><vp x="0" y="5" z="-6"/></o></c><c d="01_block" t="0"><o r="1,0,0,0,0,-1,0,1,0" bc="FFFFFFFF" ac="FFFFFFFF" sc="6"><vp x="0" y="6" z="-6"/></o></c><c d="01_block" t="0"><o r="1,0,0,0,0,-1,0,1,0" bc="FFFFFFFF" ac="FFFFFFFF" sc="6"><vp x="0" y="7" z="-6"/></o></c><c d="01_block" t="0"><o r="1,0,0,0,0,-1,0,1,0" bc="FFFFFFFF" ac="FFFFFFFF" sc="6"><vp x="0" y="8" z="-6"/></o></c><c d="01_block" t="0"><o r="1,0,0,0,0,-1,0,1,0" bc="FFFFFFFF" ac="FFFFFFFF" sc="6"><vp x="0" y="9" z="-6"/></o></c><c d="01_block" t="0"><o r="1,0,0,0,0,-1,0,1,0" bc="FFFFFFFF" ac="FFFFFFFF" sc="6"><vp x="0" y="10" z="-6"/></o></c><c d="01_block" t="0"><o r="1,0,0,0,0,-1,0,1,0" bc="FFFFFFFF" ac="FFFFFFFF" sc="6"><vp x="0" y="11" z="-6"/></o></c><c d="01_block" t="0"><o r="1,0,0,0,0,-1,0,1,0" bc="FFFFFFFF" ac="FFFFFFFF" sc="6"><vp x="0" y="12" z="-6"/></o></c><c d="01_block" t="0"><o r="1,0,0,0,0,-1,0,1,0" bc="FFFFFFFF" ac="FFFFFFFF" sc="6"><vp x="0" y="13" z="-6"/></o></c><c d="01_block" t="0"><o r="1,0,0,0,0,-1,0,1,0" bc="FFFFFFFF" ac="FFFFFFFF" sc="6"><vp x="0" y="14" z="-6"/></o></c><c d="01_block" t="0"><o r="1,0,0,0,0,-1,0,1,0" bc="FFFFFFFF" ac="FFFFFFFF" sc="6"><vp x="0" y="15" z="-6"/></o></c><c d="01_block" t="0"><o r="1,0,0,0,0,-1,0,1,0" bc="FFFFFFFF" ac="FFFFFFFF" sc="6"><vp x="0" y="16" z="-6"/></o></c><c d="01_block" t="0"><o r="1,0,0,0,0,-1,0,1,0" bc="FFFFFFFF" ac="FFFFFFFF" sc="6"><vp x="0" y="17" z="-6"/></o></c><c d="01_block" t="0"><o r="1,0,0,0,0,-1,0,1,0" bc="FFFFFFFF" ac="FFFFFFFF" sc="6"><vp x="0" y="18" z="-6"/></o></c><c d="01_block" t="0"><o r="1,0,0,0,0,-1,0,1,0" bc="FFFFFFFF" ac="FFFFFFFF" sc="6"><vp x="0" y="19" z="-6"/></o></c><c d="01_block" t="0"><o r="1,0,0,0,1,0,0,0,1" bc="FFFFFFFF" ac="FFFFFFFF" sc="6"><vp x="0" y="20" z="-5"/></o></c><c d="01_block" t="0"><o r="1,0,0,0,1,0,0,0,1" bc="FFFFFFFF" ac="FFFFFFFF" sc="6"><vp x="0" y="20" z="-4"/></o></c><c d="01_block" t="0"><o r="1,0,0,0,1,0,0,0,1" bc="FFFFFFFF" ac="FFFFFFFF" sc="6"><vp x="0" y="20" z="-3"/></o></c><c d="01_block" t="0"><o r="-1,0,0,0,-1,0,0,0,1" bc="FFFFFFFF" ac="FFFFFFFF" sc="6"><vp x="0" y="0" z="-6"/></o></c><c d="01_block" t="0"><o r="-1,0,0,0,-1,0,0,0,1" bc="FFFFFFFF" ac="FFFFFFFF" sc="6"><vp x="0" y="0" z="-5"/></o></c><c d="01_block" t="0"><o r="-1,0,0,0,-1,0,0,0,1" bc="FFFFFFFF" ac="FFFFFFFF" sc="6"><vp x="0" y="0" z="-4"/></o></c><c d="01_block" t="0"><o r="-1,0,0,0,-1,0,0,0,1" bc="FFFFFFFF" ac="FFFFFFFF" sc="6"><vp x="0" y="0" z="-3"/></o></c><c d="01_block" t="0"><o r="-1,0,0,0,-1,0,0,0,1" bc="FFFFFFFF" ac="FFFFFFFF" sc="6"><vp x="0" y="0" z="-2"/></o></c><c d="01_block" t="0"><o r="0,0,1,-1,0,0,0,-1,0" bc="FFFFFFFF" ac="FFFFFFFF" sc="6"><vp x="-1" y="0" z="-4"/></o></c><c d="01_block" t="0"><o r="0,0,-1,1,0,0,0,-1,0" bc="FFFFFFFF" ac="FFFFFFFF" sc="6"><vp x="1" y="0" z="-4"/></o></c><c d="01_block" t="0"><o r="0,0,-1,1,0,0,0,-1,0" bc="FFFFFFFF" ac="FFFFFFFF" sc="6"><vp x="2" y="0" z="-4"/></o></c><c d="01_block" t="0"><o r="0,0,-1,1,0,0,0,-1,0" bc="FFFFFFFF" ac="FFFFFFFF" sc="6"><vp x="3" y="0" z="-4"/></o></c><c d="01_block" t="0"><o r="0,0,-1,1,0,0,0,-1,0" bc="FFFFFFFF" ac="FFFFFFFF" sc="6"><vp x="4" y="0" z="-4"/></o></c><c d="01_block" t="0"><o r="1,0,0,0,0,-1,0,1,0" bc="FFFFFFFF" ac="FFFFFFFF" sc="6"><vp x="0" y="1" z="-7"/></o></c><c d="01_block" t="0"><o r="1,0,0,0,0,-1,0,1,0" bc="FFFFFFFF" ac="FFFFFFFF" sc="6"><vp x="0" y="2" z="-7"/></o></c><c d="01_block" t="0"><o r="1,0,0,0,0,-1,0,1,0" bc="FFFFFFFF" ac="FFFFFFFF" sc="6"><vp x="0" y="3" z="-7"/></o></c><c d="01_block" t="0"><o r="1,0,0,0,0,-1,0,1,0" bc="FFFFFFFF" ac="FFFFFFFF" sc="6"><vp x="0" y="1" z="-8"/></o></c><c d="01_block" t="0"><o r="0,0,-1,1,0,0,0,-1,0" bc="FFFFFFFF" ac="FFFFFFFF" sc="6"><vp x="0" y="0" z="-8"/></o></c><c d="01_block" t="0"><o r="0,0,-1,1,0,0,0,-1,0" bc="FFFFFFFF" ac="FFFFFFFF" sc="6"><vp x="0" y="1" z="-9"/></o></c><c d="01_block" t="0"><o r="0,0,-1,1,0,0,0,-1,0" bc="FFFFFFFF" ac="FFFFFFFF" sc="6"><vp x="0" y="2" z="-9"/></o></c><c d="01_block" t="0"><o r="0,0,-1,1,0,0,0,-1,0" bc="FFFFFFFF" ac="FFFFFFFF" sc="6"><vp x="0" y="2" z="-8"/></o></c><c d="01_block" t="0"><o r="0,0,-1,1,0,0,0,-1,0" bc="FFFFFFFF" ac="FFFFFFFF" sc="6"><vp x="0" y="3" z="-9"/></o></c><c d="01_block" t="0"><o r="0,0,-1,1,0,0,0,-1,0" bc="FFFFFFFF" ac="FFFFFFFF" sc="6"><vp x="0" y="3" z="-8"/></o></c><c d="01_block" t="0"><o r="0,0,-1,1,0,0,0,-1,0" bc="FFFFFFFF" ac="FFFFFFFF" sc="6"><vp x="0" y="4" z="-9"/></o></c><c d="01_block" t="0"><o r="0,0,-1,1,0,0,0,-1,0" bc="FFFFFFFF" ac="FFFFFFFF" sc="6"><vp x="0" y="4" z="-8"/></o></c><c d="01_block" t="0"><o r="0,0,-1,1,0,0,0,-1,0" bc="FFFFFFFF" ac="FFFFFFFF" sc="6"><vp x="0" y="0" z="-9"/></o></c><c d="01_block" t="0"><o r="0,0,-1,1,0,0,0,-1,0" bc="FFFFFFFF" ac="FFFFFFFF" sc="6"><vp x="0" y="1" z="-10"/></o></c><c d="01_block" t="0"><o r="0,0,-1,1,0,0,0,-1,0" bc="FFFFFFFF" ac="FFFFFFFF" sc="6"><vp x="0" y="2" z="-10"/></o></c><c d="01_block" t="0"><o r="0,0,-1,1,0,0,0,-1,0" bc="FFFFFFFF" ac="FFFFFFFF" sc="6"><vp x="0" y="3" z="-10"/></o></c><c d="01_block" t="0"><o r="0,0,-1,1,0,0,0,-1,0" bc="FFFFFFFF" ac="FFFFFFFF" sc="6"><vp x="0" y="4" z="-10"/></o></c><c d="01_block" t="0"><o r="0,0,-1,1,0,0,0,-1,0" bc="FFFFFFFF" ac="FFFFFFFF" sc="6"><vp x="0" y="0" z="-10"/></o></c><c d="01_block" t="0"><o r="1,0,0,0,0,-1,0,1,0" bc="FFFFFFFF" ac="FFFFFFFF" sc="6"><vp x="0" y="1" z="-11"/></o></c><c d="01_block" t="0"><o r="1,0,0,0,0,-1,0,1,0" bc="FFFFFFFF" ac="FFFFFFFF" sc="6"><vp x="0" y="2" z="-11"/></o></c><c d="01_block" t="0"><o r="1,0,0,0,0,-1,0,1,0" bc="FFFFFFFF" ac="FFFFFFFF" sc="6"><vp x="0" y="3" z="-11"/></o></c></components></body></bodies><logic_node_links/></vehicle>